doc/__init__.py
doc/hellow.py
testpos/__init__.py
testpos/hellow.py
testpos-0.0.4.dist-info/LICENSE
testpos-0.0.4.dist-info/METADATA
testpos-0.0.4.dist-info/WHEEL
testpos-0.0.4.dist-info/top_level.txt
testpos-0.0.4.dist-info/RECORD
