Metadata-Version: 2.1
Name: testpos
Version: 0.0.4
Summary: PyPI Tutorial
Home-page: https://github.com/
Author: leevv
Author-email: lwtaurus@163.com
License: UNKNOWN
Platform: UNKNOWN
Classifier: Programming Language :: Python :: 3
Classifier: License :: OSI Approved :: MIT License
Classifier: Operating System :: OS Independent
